{
  "cli": {
    "version": ">= 2.2.0"
  },
  "build": {
    "base": {
      "env": {}
    },
    "development": {
      "developmentClient": true,
      "distribution": "internal"
    },
    "preview": {
      "distribution": "internal",
      "ios": {
        "image": "latest"
      },
      "env": {
        "EXPO_PUBLIC_BASE_URL": "EXPO_PUBLIC_BASE_URL",
        "EXPO_PUBLIC_CLIENT_ID": "EXPO_PUBLIC_CLIENT_ID",
        "EXPO_PUBLIC_CLIENT_SECRET_VALUE": "EXPO_PUBLIC_CLIENT_SECRET_VALUE",
        "EXPO_PUBLIC_CLIENT_SECRET_ID": "EXPO_PUBLIC_CLIENT_SECRET_ID"
      }
    },
    "production": {},
    "development-simulator": {
      "developmentClient": true,
      "distribution": "internal",
      "ios": {
        "simulator": true
      }
    },
    "devclient": {
      "extends": "base",
      "channel": "default",
      "distribution": "internal",
      "developmentClient": true,
      "android": {
        "buildType": "apk"
      },
      "ios": {
        "simulator": true,
        "image": "latest",
        "autoIncrement": "version"
      }
    }
  },
  "submit": {
    "production": {}
  }
}
